llama_index/embeddings/oracleai/__init__.py
llama_index/embeddings/oracleai/base.py
llama_index_embeddings_oracleai-0.3.1.dist-info/METADATA
llama_index_embeddings_oracleai-0.3.1.dist-info/WHEEL
llama_index_embeddings_oracleai-0.3.1.dist-info/licenses/LICENSE
llama_index_embeddings_oracleai-0.3.1.dist-info/RECORD
