Metadata-Version: 2.4
Name: llama-index-embeddings-oracleai
Version: 0.3.1
Summary: llama-index embeddings oracleai integration
Author-email: Your Name <you@example.com>
License-Expression: MIT
License-File: LICENSE
Requires-Python: <4.0,>=3.9
Requires-Dist: llama-index-core>=0.11.1
Requires-Dist: oracledb>=2.2
